django_hstore/__init__.py
django_hstore/apps.py
django_hstore/compat.py
django_hstore/descriptors.py
django_hstore/dict.py
django_hstore/exceptions.py
django_hstore/fields.py
django_hstore/forms.py
django_hstore/hstore.py
django_hstore/lookups.py
django_hstore/managers.py
django_hstore/models.py
django_hstore/query.py
django_hstore/utils.py
django_hstore/virtual.py
django_hstore/widgets.py
django_hstore/__pycache__/__init__.cpython-34.pyc
django_hstore/__pycache__/apps.cpython-34.pyc
django_hstore/__pycache__/compat.cpython-34.pyc
django_hstore/__pycache__/descriptors.cpython-34.pyc
django_hstore/__pycache__/dict.cpython-34.pyc
django_hstore/__pycache__/exceptions.cpython-34.pyc
django_hstore/__pycache__/fields.cpython-34.pyc
django_hstore/__pycache__/forms.cpython-34.pyc
django_hstore/__pycache__/hstore.cpython-34.pyc
django_hstore/__pycache__/lookups.cpython-34.pyc
django_hstore/__pycache__/managers.cpython-34.pyc
django_hstore/__pycache__/models.cpython-34.pyc
django_hstore/__pycache__/query.cpython-34.pyc
django_hstore/__pycache__/utils.cpython-34.pyc
django_hstore/__pycache__/virtual.cpython-34.pyc
django_hstore/__pycache__/widgets.cpython-34.pyc
django_hstore/static/admin/js/django_hstore/hstore-widget.js
django_hstore/static/admin/js/django_hstore/underscore-min.js
django_hstore/templates/hstore_default_widget.html
django_hstore/templates/hstore_grappelli_widget.html
django_hstore-1.4.2.dist-info/DESCRIPTION.rst
django_hstore-1.4.2.dist-info/METADATA
django_hstore-1.4.2.dist-info/RECORD
django_hstore-1.4.2.dist-info/WHEEL
django_hstore-1.4.2.dist-info/metadata.json
django_hstore-1.4.2.dist-info/top_level.txt
