Metadata-Version: 1.1
Name: django-hstore
Version: 1.4.2
Summary: PostgreSQL HStore support for Django
Home-page: https://github.com/djangonauts/django-hstore
Author: Djangonauts Organization
Author-email: django-hstore@googlegroups.com
License: BSD
Download-URL: https://github.com/djangonauts/django-hstore/releases
Keywords: django,hstore,schemaless
Platform: Platform Indipendent
Classifier: Development Status :: 4 - Beta
Classifier: Environment :: Web Environment
Classifier: Intended Audience :: Developers
Classifier: License :: OSI Approved :: BSD License
Classifier: Operating System :: OS Independent
Classifier: Programming Language :: Python
Classifier: Topic :: Internet :: WWW/HTTP :: Dynamic Content
Classifier: Framework :: Django
Classifier: Programming Language :: Python
Classifier: Programming Language :: Python :: 2.6
Classifier: Programming Language :: Python :: 2.7
Classifier: Programming Language :: Python :: 3
Classifier: Programming Language :: Python :: 3.3
Classifier: Programming Language :: Python :: 3.4
